pyorick/__init__.py
pyorick/pyorick.i0
pyorick/pyorick.py
pyorick/test_pyorick.py
pyorick-1.5.dist-info/LICENSE.txt
pyorick-1.5.dist-info/METADATA
pyorick-1.5.dist-info/WHEEL
pyorick-1.5.dist-info/top_level.txt
pyorick-1.5.dist-info/RECORD
