Metadata-Version: 2.1
Name: pyorick
Version: 1.5
Summary: python connection to yorick
Home-page: https://github.com/dhmunro/pyorick
Author: David Munro and John Field
Author-email: dhmunro@users.sourceforge.net
License: http://opensource.org/licenses/BSD-2-Clause
Platform: Linux
Platform: MacOS X
Platform: Unix
Classifier: License :: OSI Approved :: BSD License
Classifier: Programming Language :: Python :: 2.7
Classifier: Programming Language :: Python :: 3
Classifier: Operating System :: POSIX :: Linux
Classifier: Operating System :: MacOS :: MacOS X
Classifier: Operating System :: Unix
Classifier: Topic :: Scientific/Engineering
Classifier: Topic :: Software Development :: Interpreters
Requires: numpy
License-File: LICENSE.txt
